utilsx/__init__.py
utilsx/collections.py
utilsx/decorators.py
utilsx/exceptions.py
utilsx/functional.py
utilsx/py.typed
utilsx/text.py
utilsx/typevars.py
utilsx/constants/__init__.py
utilsx/constants/_numbers.py
utilsx/constants/_physics.py
utilsx/constants/_time.py
utilsx/dicts/__init__.py
utilsx/dicts/_combination.py
utilsx/dicts/_filtering.py
utilsx/dicts/_modification.py
utilsx/dicts/_sorting.py
utilsx/math/__init__.py
utilsx/math/_collections.py
utilsx/math/_division.py
utilsx/math/_downscaling.py
utilsx/math/_rounding.py
utilsx/math/_scalar_ops.py
utilsx/pandas/__init__.py
utilsx/pandas/_missing.py
utilsx-0.0.0a5.dist-info/METADATA
utilsx-0.0.0a5.dist-info/WHEEL
utilsx-0.0.0a5.dist-info/licenses/LICENSE
utilsx-0.0.0a5.dist-info/RECORD
