Metadata-Version: 2.4
Name: utilsx
Version: 0.0.0a5
Summary: A collection of useful constants and generic functions for Python
Author-email: Yury Fedotov <author@example.com>
License-Expression: MIT
License-File: LICENSE
Classifier: Operating System :: OS Independent
Classifier: Programming Language :: Python :: 3
Requires-Python: >=3.10
Provides-Extra: all
Requires-Dist: pandas>=1.5; extra == 'all'
Provides-Extra: pandas
Requires-Dist: pandas>=1.5; extra == 'pandas'
